Metadata-Version: 1.0
Name: gamification
Version: 0.0.3
Summary: UNKNOWN
Home-page: https://github.com/monzita/gamification
Author: Monika Ilieva
Author-email: example@hidden.com
License: MIT License
Keywords: game console
Platform: UNKNOWN
